sdu/__init__.py
sdu/autocomplete.py
sdu/cli.py
sdu/paths.py
sdu/type_conversions.py
sdu/validation.py
sdu-0.1.2.dist-info/LICENSE
sdu-0.1.2.dist-info/METADATA
sdu-0.1.2.dist-info/WHEEL
sdu-0.1.2.dist-info/top_level.txt
sdu-0.1.2.dist-info/RECORD
