Metadata-Version: 2.1
Name: sdu
Version: 0.1.2
Summary: A set of utilites to make developing scripts simpler and easier
Home-page: https://github.com/Descent098/sdu
Author: Kieran Wood
Author-email: kieran@canadiancoding.ca
License: UNKNOWN
Platform: UNKNOWN
Classifier: Programming Language :: Python :: 3
Classifier: Operating System :: OS Independent
Classifier: Development Status :: 4 - Beta
Requires-Dist: colored
Provides-Extra: dev
Requires-Dist: nox ; extra == 'dev'
Requires-Dist: pytest ; extra == 'dev'
Requires-Dist: pdoc3 ; extra == 'dev'
